fred_timeseries_toolkit/__init__.py
fred_timeseries_toolkit/ts_toolkit.py
fred_timeseries_toolkit-0.1.4.dist-info/METADATA
fred_timeseries_toolkit-0.1.4.dist-info/WHEEL
fred_timeseries_toolkit-0.1.4.dist-info/top_level.txt
fred_timeseries_toolkit-0.1.4.dist-info/RECORD
