Metadata-Version: 2.4
Name: fred-timeseries-toolkit
Version: 0.1.4
Summary: A toolkit for time series analysis and forecasting with FRED integration.
Author: Rory G. Quinlan
License: MIT
Project-URL: Homepage, https://github.com/roryqo/FRED-Timeseries-Analysis-Package
Project-URL: Repository, https://github.com/roryqo/FRED-Timeseries-Analysis-Package
Requires-Python: >=3.7
Requires-Dist: pandas
Requires-Dist: numpy
Requires-Dist: matplotlib
Requires-Dist: fredapi
Requires-Dist: statsmodels
Requires-Dist: IPython
